[
  {
    "diaryID": 12,
    "year": 2017,
    "month": 3,
    "day": 14,
    "likes": 5,
    "components": [
      {
        "photo": "https://lh3.googleusercontent.com/7GVRHWwJovGNnxWIvmGznJzurEcUJSYP1nvmL6Iixd5h=s640-no",
        "text": "hogehoge",
        "hour": 14
      },
      {
        "photo": "https://pbs.twimg.com/profile_images/718091260070727680/WIb00R__.jpg",
        "text": "hogehoge",
        "hour": 16
      }
    ],
    "user": {
      "name": "sampleuser",
      "userID": 1,
      "icon": "https://lh3.googleusercontent.com/7GVRHWwJovGNnxWIvmGznJzurEcUJSYP1nvmL6Iixd5h"
    }
  },
  {
    "diaryID": 13,
    "year": 2017,
    "month": 3,
    "day": 12,
    "likes": 21,
    "components": [
      {
        "photo": "https://job.cinra.net/assets/uploads/2015/03/roaster_cover1.jpg",
        "text": "hogehogehogehoge",
        "hour": 12
      },
      {
        "photo": "https://tabelog.ssl.k-img.com/restaurant/images/Rvw/56403/640x640_rect_56403967.jpg",
        "text": "hogehogehogehoge",
        "hour": 19
      }
    ],
    "user": {
      "name": "sampleuser",
      "userID": 1,
      "icon": "https://job.cinra.net/assets/uploads/2015/03/roaster_cover1.jpg"
    }
  },
  {
    "diaryID": 14,
    "year": 2017,
    "month": 3,
    "day": 12,
    "likes": 21,
    "components": [
      {
        "photo": "https://job.cinra.net/assets/uploads/2015/03/roaster_cover1.jpg",
        "text": "hogehogehogehoge",
        "hour": 12
      },
      {
        "photo": "https://tabelog.ssl.k-img.com/restaurant/images/Rvw/56403/640x640_rect_56403967.jpg",
        "text": "hogehogehogehoge",
        "hour": 19
      }
    ],
    "user": {
      "name": "sampleuser",
      "userID": 1,
      "icon": "https://job.cinra.net/assets/uploads/2015/03/roaster_cover1.jpg"
    }
  }
]
